{
  "ok": true,
  "active": [
    {
      "parcel_id": "P01",
      "parcel_name": "Пшеница",
      "culture": "Пшеница",
      "area_ha": 0.54,
      "acquisition": "2026-06-24",
      "type": "drought_stress",
      "label": "Сушни стрес",
      "level": "warning",
      "color": "#f6c95f",
      "icon": "💧",
      "evidence": [
        {
          "index": "ndmi",
          "current": 0.2579,
          "baseline": 0.3558,
          "delta": -0.0979,
          "threshold": "drop>=0.08 over 7d"
        },
        {
          "index": "ndre",
          "current": 0.365,
          "baseline": 0.5032,
          "delta": -0.1382,
          "threshold": "drop>=0.05 over 7d"
        }
      ],
      "logic": "OR"
    },
    {
      "parcel_id": "P01",
      "parcel_name": "Пшеница",
      "culture": "Пшеница",
      "area_ha": 0.54,
      "acquisition": "2026-06-24",
      "type": "vitality_drop",
      "label": "Пад виталности",
      "level": "warning",
      "color": "#f6c95f",
      "icon": "🌿",
      "evidence": [
        {
          "index": "ndvi",
          "current": 0.6392,
          "baseline": 0.7658,
          "delta": -0.1266,
          "threshold": "drop>=0.08 over 7d"
        }
      ],
      "logic": "AND"
    },
    {
      "parcel_id": "P02",
      "parcel_name": "Пашњак",
      "culture": "Пашњак",
      "area_ha": 0.23,
      "acquisition": "2026-06-24",
      "type": "drought_stress",
      "label": "Сушни стрес",
      "level": "warning",
      "color": "#f6c95f",
      "icon": "💧",
      "evidence": [
        {
          "index": "ndmi",
          "current": 0.0442,
          "baseline": 0.104,
          "delta": -0.0598,
          "threshold": "drop>=0.08 over 7d"
        },
        {
          "index": "ndre",
          "current": 0.3342,
          "baseline": 0.3887,
          "delta": -0.0545,
          "threshold": "drop>=0.05 over 7d"
        }
      ],
      "logic": "OR"
    },
    {
      "parcel_id": "P03",
      "parcel_name": "Кромпир",
      "culture": "Кромпир",
      "area_ha": 0.37,
      "acquisition": "2026-06-24",
      "type": "recovery",
      "label": "Опоравак",
      "level": "info",
      "color": "#7cc26b",
      "icon": "🌱",
      "evidence": [
        {
          "index": "ndvi",
          "current": 0.4595,
          "baseline": 0.3554,
          "delta": 0.1041,
          "threshold": "gain>=0.05 over 7d"
        }
      ],
      "logic": "AND"
    },
    {
      "parcel_id": "P04",
      "parcel_name": "Кромпир",
      "culture": "Кромпир",
      "area_ha": 0.57,
      "acquisition": "2026-06-24",
      "type": "recovery",
      "label": "Опоравак",
      "level": "info",
      "color": "#7cc26b",
      "icon": "🌱",
      "evidence": [
        {
          "index": "ndvi",
          "current": 0.5807,
          "baseline": 0.4507,
          "delta": 0.13,
          "threshold": "gain>=0.05 over 7d"
        }
      ],
      "logic": "AND"
    },
    {
      "parcel_id": "P05",
      "parcel_name": "Пшеница",
      "culture": "Пшеница",
      "area_ha": 0.73,
      "acquisition": "2026-06-24",
      "type": "drought_stress",
      "label": "Сушни стрес",
      "level": "warning",
      "color": "#f6c95f",
      "icon": "💧",
      "evidence": [
        {
          "index": "ndmi",
          "current": 0.2988,
          "baseline": 0.3836,
          "delta": -0.0848,
          "threshold": "drop>=0.08 over 7d"
        },
        {
          "index": "ndre",
          "current": 0.3861,
          "baseline": 0.5109,
          "delta": -0.1248,
          "threshold": "drop>=0.05 over 7d"
        }
      ],
      "logic": "OR"
    },
    {
      "parcel_id": "P05",
      "parcel_name": "Пшеница",
      "culture": "Пшеница",
      "area_ha": 0.73,
      "acquisition": "2026-06-24",
      "type": "vitality_drop",
      "label": "Пад виталности",
      "level": "warning",
      "color": "#f6c95f",
      "icon": "🌿",
      "evidence": [
        {
          "index": "ndvi",
          "current": 0.6807,
          "baseline": 0.7915,
          "delta": -0.1108,
          "threshold": "drop>=0.08 over 7d"
        }
      ],
      "logic": "AND"
    },
    {
      "parcel_id": "P06",
      "parcel_name": "Пашњак",
      "culture": "Пашњак",
      "area_ha": 0.31,
      "acquisition": "2026-06-24",
      "type": "drought_stress",
      "label": "Сушни стрес",
      "level": "warning",
      "color": "#f6c95f",
      "icon": "💧",
      "evidence": [
        {
          "index": "ndmi",
          "current": 0.1167,
          "baseline": 0.1847,
          "delta": -0.068,
          "threshold": "drop>=0.08 over 7d"
        },
        {
          "index": "ndre",
          "current": 0.3327,
          "baseline": 0.4267,
          "delta": -0.094,
          "threshold": "drop>=0.05 over 7d"
        }
      ],
      "logic": "OR"
    },
    {
      "parcel_id": "P06",
      "parcel_name": "Пашњак",
      "culture": "Пашњак",
      "area_ha": 0.31,
      "acquisition": "2026-06-24",
      "type": "vitality_drop",
      "label": "Пад виталности",
      "level": "warning",
      "color": "#f6c95f",
      "icon": "🌿",
      "evidence": [
        {
          "index": "ndvi",
          "current": 0.643,
          "baseline": 0.7246,
          "delta": -0.0816,
          "threshold": "drop>=0.08 over 7d"
        }
      ],
      "logic": "AND"
    },
    {
      "parcel_id": "P07",
      "parcel_name": "Ливада",
      "culture": "Ливада",
      "area_ha": 0.51,
      "acquisition": "2026-06-24",
      "type": "drought_stress",
      "label": "Сушни стрес",
      "level": "warning",
      "color": "#f6c95f",
      "icon": "💧",
      "evidence": [
        {
          "index": "ndmi",
          "current": 0.2832,
          "baseline": 0.3139,
          "delta": -0.0307,
          "threshold": "drop>=0.08 over 7d"
        },
        {
          "index": "ndre",
          "current": 0.3929,
          "baseline": 0.4934,
          "delta": -0.1005,
          "threshold": "drop>=0.05 over 7d"
        }
      ],
      "logic": "OR"
    },
    {
      "parcel_id": "P07",
      "parcel_name": "Ливада",
      "culture": "Ливада",
      "area_ha": 0.51,
      "acquisition": "2026-06-24",
      "type": "vitality_drop",
      "label": "Пад виталности",
      "level": "warning",
      "color": "#f6c95f",
      "icon": "🌿",
      "evidence": [
        {
          "index": "ndvi",
          "current": 0.6808,
          "baseline": 0.8083,
          "delta": -0.1275,
          "threshold": "drop>=0.08 over 7d"
        }
      ],
      "logic": "AND"
    }
  ],
  "count": 11,
  "by_level": {
    "critical": 0,
    "warning": 9,
    "info": 2
  },
  "latest_acquisition": "2026-06-24",
  "generated_at": "2026-06-26T08:34:01Z"
}